imgdif/__init__.py
imgdif/command_line.py
imgdif1-0.2.dist-info/METADATA
imgdif1-0.2.dist-info/WHEEL
imgdif1-0.2.dist-info/entry_points.txt
imgdif1-0.2.dist-info/top_level.txt
imgdif1-0.2.dist-info/RECORD
