Metadata-Version: 2.1
Name: imgdif1
Version: 0.2
Summary: Compares two images
Home-page: http://github.com/storborg/funniest
Author: DevOps Academy
Author-email: devopsacamedy@example.com
License: MIT
Platform: UNKNOWN
